LICENSE
README.md
setup.py
vinted/__init__.py
vinted/endpoints.py
vinted/exceptions.py
vinted/response_codes.py
vinted/utils.py
vinted/vinted.py
vinted/models/__init__.py
vinted/models/base.py
vinted/models/filters.py
vinted/models/items.py
vinted/models/money.py
vinted/models/other.py
vinted/models/photos.py
vinted/models/search.py
vinted/models/users.py
vinted_api_wrapper.egg-info/PKG-INFO
vinted_api_wrapper.egg-info/SOURCES.txt
vinted_api_wrapper.egg-info/dependency_links.txt
vinted_api_wrapper.egg-info/requires.txt
vinted_api_wrapper.egg-info/top_level.txt